PyGeoRaster/GeoTiffSegmentation.py
PyGeoRaster/__init__.py
PyGeoRaster-1.0.1.dist-info/METADATA
PyGeoRaster-1.0.1.dist-info/WHEEL
PyGeoRaster-1.0.1.dist-info/top_level.txt
PyGeoRaster-1.0.1.dist-info/RECORD
